in8utils/__init__.py
in8utils/aws.py
in8utils/database.py
in8utils/general.py
in8utils/http.py
in8utils/string.py
in8utils-1.0.43.dist-info/LICENSE
in8utils-1.0.43.dist-info/METADATA
in8utils-1.0.43.dist-info/WHEEL
in8utils-1.0.43.dist-info/top_level.txt
in8utils-1.0.43.dist-info/RECORD
